[{"id":1,"cliente":{"idCliente":1,"nome":"Tiago Secundo","telefone":"33 991565427","endereco":"rua A","cpf":"13744792684","email":"tiago@"},"veiculo":{"marca":"a","modelo":"a","ano":2222,"placa":"1a","status":"a","proprietario":{"idCliente":1,"nome":"Tiago Secundo","telefone":"33 991565427","endereco":"rua A","cpf":"13744792684","email":"tiago@"},"historicoServicos":[],"relatorio":"a"},"problemaDescrito":"sadas","mecanicoResponsavel":{"especialidade":"freios","id":1,"nome":"luiz","cargo":"mecanico","email":"s","salario":5555.0,"ponto":{}},"dataHora":"2025-06-30T14:00:00","status":"Cancelado","elevador":{"id":1,"status":"Ocupado","veiculoNaPlataforma":"1a","servicoEmExecucao":"sadas"},"agendamentos":[]}]